{
  "en": {
    "homeTitle": "NailssxMocha",
    "homeSubtitle": "Gel X • Builder Gel • Rubber Gel",
    "bookBtn": "Book Appointment",
    "servicesTitle": "Services & Pricing",
    "serviceGelX": "Gel X",
    "short": "Short (1–2 magnet)",
    "medium": "Medium (3–4 magnet)",
    "long": "Long (5–7 magnet)",
    "xlong": "X Long (8–10 magnet)",
    "manicure": "Manicure",
    "natural": "Natural Nail or Extension",
    "classicGel": "Classic Gel Color",
    "rubberGel": "Rubber Gel",
    "builderGel": "Builder Gel",
    "pedicure": "Pedicure",
    "classic": "Classic",
    "deluxe": "Deluxe",
    "soakOff": "Soak Off",
    "foreignSoak": "Foreign Soak Off",
    "galleryTitle": "Featured Nails",
    "viewGallery": "View Full Gallery",
    "instagram": "Follow us on Instagram",
    "navHome": "Home",
    "navServices": "Services",
    "navGallery": "Gallery",
    "navPolicy": "Policy",
    "navBook": "Book"
  },
  "es": {
    "homeTitle": "NailssxMocha",
    "homeSubtitle": "Gel X • Builder Gel • Gel de Goma",
    "bookBtn": "Reservar Cita",
    "servicesTitle": "Servicios y Precios",
    "serviceGelX": "Gel X",
    "short": "Corto (1–2 imán)",
    "medium": "Medio (3–4 imán)",
    "long": "Largo (5–7 imán)",
    "xlong": "Extra Largo (8–10 imán)",
    "manicure": "Manicura",
    "natural": "Uña Natural o Extensión",
    "classicGel": "Color Gel Clásico",
    "rubberGel": "Gel de Goma",
    "builderGel": "Builder Gel",
    "pedicure": "Pedicura",
    "classic": "Clásico",
    "deluxe": "De Lujo",
    "soakOff": "Retirar Gel",
    "foreignSoak": "Retirar Gel Extranjero",
    "galleryTitle": "Uñas Destacadas",
    "viewGallery": "Ver Galería Completa",
    "instagram": "Síguenos en Instagram",
    "navHome": "Inicio",
    "navServices": "Servicios",
    "navGallery": "Galería",
    "navPolicy": "Políticas",
    "navBook": "Reservar"
  }
}